{
  "msg": "操作成功",
  "suc": true,
  "traceId": "8198f2470f8483c8469896bc69f3f1aa",
  "code": "200",
  "data": {
    "seParams": {},
    "requestId": "4305e184dce44bf18c99cd0bcc9b9a4b",
    "apiData": {
      "apiRecall": [
        {
          "tag": "基金数据库",
          "type": "基金实时行情查询",
          "content": "| 市场类型 | 证券名称 | 证券代码 | 最新价格 | 昨收盘 | 今开盘 | 总成交 | 外盘 | 内盘 | 买1价 | 买1量 | 买2价 | 买2量 | 买3价 | 买3量 | 买4价 | 买4量 | 买5价 | 买5量 | 卖1价 | 卖1量 | 卖2价 | 卖2量 | 卖3价 | 卖3量 | 卖4价 | 卖4量 | 卖5价 | 卖5量 | 当天最高价格 | 当天最低价格 | 总市值 | 市净率 | 涨停价 | 跌停价 | 量比 | 委差 | 均价 | 总股本 | 委比 | 基金净值 |\n| :---: | :---: | :---: | :---: | :---: | :---: | :---: | :---: | :---: | :---: | :---: | :---: | :---: | :---: | :---: | :---: | :---: | :---: | :---: | :---: | :---: | :---: | :---: | :---: | :---: | :---: | :---: | :---: | :---: | :---: | :---: | :---: | :---: | :---: | :---: | :---: | :---: | :---: | :---: | :---: | :---: |\n| 沪市 | 港股创新药ETF广发 | 513120.SH | 1.187 | 1.142 | 1.140 | 73251269 | 39206371 | 34044898 | 1.187 | 138651 | 1.186 | 59622 | 1.185 | 42889 | 1.184 | 8244 | 1.183 | 40174 | 1.188 | 13884 | 1.189 | 22695 | 1.190 | 42539 | 1.191 | 29682 | 1.192 | 100343 | 1.194 | 1.126 | 271.89 | 0.00 | 1.256 | 1.028 | 1.81 | 80437 | 1.165 | 22905635400 | 16.13 | 1.1357 |",
          "desc": "基金实时行情查询"
        }
      ],
      "entity": [
        {
          "code": "港股创新药ETF广发",
          "name": "513120.SH"
        }
      ]
    },
    "extraParams": {}
  }
}
