{
  "msg": "操作成功",
  "suc": true,
  "traceId": "e45c11076743ace6c30188da228d9713",
  "code": "200",
  "data": {
    "seParams": {},
    "requestId": "79cd67c09f43471a863150deffdfe31e",
    "apiData": {
      "apiRecall": [
        {
          "tag": "股票数据库",
          "type": "今日资金流向",
          "content": "当日资金流向\n创业板指A股(代码：399006.SZ)最新资金流向资金面情况具体如下：主力净流入-16345881058元，主力流入211614616476元，占比：25%。主力流出227960497533元，占比：27%。散户流入212576646378元，占比：25%，散户流出196230765321元，占比：23%。超大单流入-13200650936元，大单流入-3145230121元，中单流入8450250779元，小单流入7895630278元。\n\n",
          "desc": "今日资金流向"
        }
      ],
      "entity": [
        {
          "code": "创业板指",
          "name": "399006.SZ"
        }
      ]
    },
    "extraParams": {}
  }
}
